porta_secura/__init__.py
porta_secura/config.py
porta_secura/main.py
porta_secura/api/__init__.py
porta_secura/api/middleware.py
porta_secura/api/routes.py
porta_secura/blockchain/__init__.py
porta_secura/blockchain/solana.py
porta_secura/blockchain/wallet.py
porta_secura/utils/__init__.py
porta_secura/utils/logging.py
porta_secura/utils/validation.py
tests/__init__.py
porta_secura-1.0.1.dist-info/LICENSE
porta_secura-1.0.1.dist-info/METADATA
porta_secura-1.0.1.dist-info/WHEEL
porta_secura-1.0.1.dist-info/top_level.txt
porta_secura-1.0.1.dist-info/RECORD
