Metadata-Version: 2.1
Name: porta-secura
Version: 1.0.1
Summary: A secure AI agent response filtering and proxy service using Solana blockchain
Home-page: https://github.com/portasecura/porta-secura
Author: PortaSecura
Author-email: contact@portasecura.io
Project-URL: Documentation, https://docs.portasecura.io
Project-URL: Source, https://github.com/portasecura/porta-secura
Project-URL: Tracker, https://github.com/portasecura/porta-secura/issues
Classifier: Development Status :: 5 - Production/Stable
Classifier: Intended Audience :: Developers
Classifier: Intended Audience :: Information Technology
Classifier: Intended Audience :: Financial and Insurance Industry
Classifier: License :: OSI Approved :: MIT License
Classifier: Operating System :: OS Independent
Classifier: Programming Language :: Python :: 3
Classifier: Programming Language :: Python :: 3.8
Classifier: Programming Language :: Python :: 3.9
Classifier: Programming Language :: Python :: 3.10
Classifier: Topic :: Security
Classifier: Topic :: Software Development :: Libraries :: Python Modules
Classifier: Topic :: System :: Systems Administration
Classifier: Framework :: FastAPI
Requires-Python: >=3.8
License-File: LICENSE
Requires-Dist: fastapi>=0.68.0
Requires-Dist: uvicorn>=0.15.0
Requires-Dist: pydantic>=1.8.2
Requires-Dist: aiohttp>=3.8.1
Requires-Dist: python-jose>=3.3.0
Requires-Dist: python-multipart>=0.0.5
Requires-Dist: certifi>=2021.10.8
Requires-Dist: redis>=4.2.0
Requires-Dist: pyjwt>=2.3.0
Provides-Extra: blockchain
Requires-Dist: solana>=0.23.0; extra == "blockchain"
Requires-Dist: spl-token>=0.2.0; extra == "blockchain"
Provides-Extra: proxy
Requires-Dist: aiohttp>=3.8.1; extra == "proxy"
Requires-Dist: certifi>=2021.10.8; extra == "proxy"
Provides-Extra: ai
Requires-Dist: spacy>=3.2.0; extra == "ai"
Requires-Dist: transformers>=4.19.0; extra == "ai"
Provides-Extra: all
Requires-Dist: solana>=0.23.0; extra == "all"
Requires-Dist: spl-token>=0.2.0; extra == "all"
Requires-Dist: aiohttp>=3.8.1; extra == "all"
Requires-Dist: certifi>=2021.10.8; extra == "all"
Requires-Dist: spacy>=3.2.0; extra == "all"
Requires-Dist: transformers>=4.19.0; extra == "all"
